pysand/__init__.py
pysand/cli.py
pysand/manager.py
pysand/backends/__init__.py
pysand/backends/docker.py
pysand/backends/virtualenv.py
sandboxr-0.1.1.dist-info/METADATA
sandboxr-0.1.1.dist-info/WHEEL
sandboxr-0.1.1.dist-info/entry_points.txt
sandboxr-0.1.1.dist-info/top_level.txt
sandboxr-0.1.1.dist-info/RECORD
