Metadata-Version: 2.1
Name: sandboxr
Version: 0.1.1
Summary: Quickly spin up isolated Python sandboxes (virtualenv or Docker), install dependencies, execute code, and tear down.
Home-page: https://github.com/akulka404/sandboxr
Author: Ani Kulkarni
Author-email: aniruddha.k1911@gmail.com
Keywords: sandbox,virtualenv,docker,automation,cli
Classifier: Programming Language :: Python :: 3
Classifier: License :: OSI Approved :: MIT License
Classifier: Operating System :: OS Independent
Classifier: Intended Audience :: Developers
Requires-Python: >=3.6
